rocketchat_2fa_check/__init__.py
rocketchat_2fa_check/__main__.py
rocketchat_2fa_check/checker.py
rocketchat_2fa_check/cli.py
rocketchat_2fa_check-0.3.1.dist-info/entry_points.txt
rocketchat_2fa_check-0.3.1.dist-info/LICENSE
rocketchat_2fa_check-0.3.1.dist-info/WHEEL
rocketchat_2fa_check-0.3.1.dist-info/METADATA
rocketchat_2fa_check-0.3.1.dist-info/RECORD
