Metadata-Version: 2.1
Name: rocketchat-2fa-check
Version: 0.3.1
Summary: 
Author: Ulrich Petri
Author-email: github@ulo.pe
Requires-Python: >=3.9,<4.0
Classifier: Programming Language :: Python :: 3
Classifier: Programming Language :: Python :: 3.9
Requires-Dist: click (>=7.0,<8.0)
Requires-Dist: click-pathlib (>=2020.3.13,<2021.0.0)
Requires-Dist: pymongo (>=3.8,<4.0)
Requires-Dist: requests (>=2.22,<3.0)
